nowpy/__init__.py
nowpy/main.py
nowpy-0.1.6.dist-info/LICENSE
nowpy-0.1.6.dist-info/METADATA
nowpy-0.1.6.dist-info/WHEEL
nowpy-0.1.6.dist-info/entry_points.txt
nowpy-0.1.6.dist-info/RECORD
