Metadata-Version: 2.1
Name: nowpy
Version: 0.1.6
Summary: Run any Python file instantly, with just one command
Home-page: https://github.com/WillDenby/nowpy
License: MIT
Author: WillDenby
Author-email: 119456795+WillDenby@users.noreply.github.com
Requires-Python: >=3.9,<4.0
Classifier: License :: OSI Approved :: MIT License
Classifier: Programming Language :: Python :: 3
Classifier: Programming Language :: Python :: 3.9
Classifier: Programming Language :: Python :: 3.10
Classifier: Programming Language :: Python :: 3.11
Classifier: Programming Language :: Python :: 3.12
Requires-Dist: toml (>=0.10.2,<0.11.0)
Requires-Dist: typeguard (>=4.3.0,<5.0.0)
Requires-Dist: typer (>=0.9.0,<0.10.0)
Requires-Dist: virtualenv (>=20.26.6,<21.0.0)
Project-URL: Repository, https://github.com/WillDenby/nowpy
